trading_service_utils/__init__.py
trading_service_utils/client/__init__.py
trading_service_utils/client/executor_client.py
trading_service_utils/fetcher/__init__.py
trading_service_utils/fetcher/pm_api.py
trading_service_utils/fetcher/pm_fetcher.py
trading_service_utils/fetcher/pm_utils.py
trading_service_utils/logging/__init__.py
trading_service_utils/notification/__init__.py
trading_service_utils/notification/service.py
trading_service_utils/notification/telegram.py
trading_service_utils-0.1.5.dist-info/METADATA
trading_service_utils-0.1.5.dist-info/WHEEL
trading_service_utils-0.1.5.dist-info/RECORD
