Metadata-Version: 2.4
Name: trading-service-utils
Version: 0.1.5
Summary: Shared utilities for trading system services
Requires-Python: >=3.12
Requires-Dist: httpx>=0.28.1
Requires-Dist: python-telegram-bot>=20.0
Requires-Dist: requests>=2.32.0
